LICENSE
vtrace/__init__.py
vtrace/app.py
vtrace/dns.py
vtrace/geo.py
vtrace/mapper.py
vtrace/traceroute.py
vtrace/utils.py
vtrace-1.0.0.dist-info/entry_points.txt
vtrace-1.0.0.dist-info/LICENSE
vtrace-1.0.0.dist-info/WHEEL
vtrace-1.0.0.dist-info/METADATA
vtrace-1.0.0.dist-info/RECORD
