Metadata-Version: 2.1
Name: vtrace
Version: 1.0.0
Summary: A command line application to trace the route to a host and provide the user with a visual map.
Home-page: https://github.com/RichardBieringa/vtrace
License: MIT
Keywords: vtrace,traceroute,visual
Author: Richard Bieringa
Author-email: richardbieringa@gmail.com
Requires-Python: >=3.10,<4.0
Classifier: License :: OSI Approved :: MIT License
Classifier: Programming Language :: Python :: 3
Classifier: Programming Language :: Python :: 3.10
Requires-Dist: click (>=8.0.3,<9.0.0)
Requires-Dist: folium (>=0.12.1,<0.13.0)
Requires-Dist: ipinfo (>=4.2.1,<5.0.0)
Requires-Dist: scapy (>=2.4.5,<3.0.0)
Project-URL: Repository, https://github.com/RichardBieringa/vtrace
